ab_testing_kit/data_splitting/sample_size_calculation.py
ab_testing_kit/exploration/data_exploration.py
ab_testing_kit/testing/tests.py
ab_testing_kit-0.1.5.dist-info/METADATA
ab_testing_kit-0.1.5.dist-info/WHEEL
ab_testing_kit-0.1.5.dist-info/top_level.txt
ab_testing_kit-0.1.5.dist-info/RECORD
